halo/__init__.py
halo/_utils.py
halo/halo.py
halo/halo_notebook.py
frkl.halo-0.0.24.dist-info/LICENSE
frkl.halo-0.0.24.dist-info/METADATA
frkl.halo-0.0.24.dist-info/WHEEL
frkl.halo-0.0.24.dist-info/top_level.txt
frkl.halo-0.0.24.dist-info/RECORD
