Metadata-Version: 2.1
Name: frkl.halo
Version: 0.0.24
Summary: Temporary fork of "halo": Beautiful terminal spinners in Python
Home-page: https://github.com/manrajgrover/halo
Author: Markus Binsteiner
Author-email: markus@frkl.io
License: MIT
Keywords: console,loading,indicator,progress,cli,spinner,spinners,terminal,term,busy,wait,idle
Platform: UNKNOWN
Requires-Dist: frkl.log-symbols (==0.0.14)
Requires-Dist: spinners (==0.0.23)
Requires-Dist: cursor (==1.2.0)
Requires-Dist: termcolor (==1.1.0)
Requires-Dist: colorama (==0.3.9)
Requires-Dist: six (==1.12.0)
Requires-Dist: backports.shutil-get-terminal-size (==1.0.0) ; python_version < "3.3"
Provides-Extra: ipython
Requires-Dist: IPython (==5.7.0) ; extra == 'ipython'
Requires-Dist: ipywidgets (==7.1.0) ; extra == 'ipython'
